setup.py
admin_ip_whitelist/__init__.py
admin_ip_whitelist/admin.py
admin_ip_whitelist/middleware.py
admin_ip_whitelist/models.py
django_admin_ip_whitelist.egg-info/PKG-INFO
django_admin_ip_whitelist.egg-info/SOURCES.txt
django_admin_ip_whitelist.egg-info/dependency_links.txt
django_admin_ip_whitelist.egg-info/top_level.txt