Metadata-Version: 1.1
Name: django-admin-ip-whitelist
Version: 0.1.1
Summary: Django middleware to allow access to /admin only for users, whose IPs are in the white list
Home-page: http://github.com/dvska/django-admin-ip-whitelist
Author: dvska
Author-email: UNKNOWN
License: Apache
Platform: Posix; MacOS X;
Classifier: Intended Audience :: Developers
Classifier: License :: OSI Approved :: Apache Software License
Classifier: Operating System :: OS Independent
Classifier: Programming Language :: Python
Classifier: Topic :: Internet :: WWW/HTTP
Classifier: Topic :: Software Development :: Libraries :: Application Frameworks
Classifier: Topic :: Software Development :: Libraries :: Python Modules
